sharehousepy/__init__.py
sharehousepy/blocks.py
sharehousepy/query.py
sharehousepy/snowflake.py
sharehousepy/data/country_geos.csv
sharehousepy-0.1.4.dist-info/METADATA
sharehousepy-0.1.4.dist-info/WHEEL
sharehousepy-0.1.4.dist-info/top_level.txt
sharehousepy-0.1.4.dist-info/RECORD
