Metadata-Version: 2.1
Name: sharehousepy
Version: 0.1.4
Summary: A python library to create and execute sharehouse queries
Author: Worthy Rae
Author-email: worthyr@anomalysix.com
Classifier: Programming Language :: Python :: 3
Classifier: Operating System :: OS Independent
Requires-Python: >=3.6
Requires-Dist: snowflake-connector-python
Requires-Dist: python-dotenv
Requires-Dist: tqdm
Requires-Dist: yaspin
Requires-Dist: shapely
Requires-Dist: python-geohash
